Metadata-Version: 1.0
Name: pandaSearch
Version: 1.0
Summary: 幻迪编程查找工具（熊猫）
Home-page: UNKNOWN
Author: 熊猫老师
Author-email: zx1411239060@163.com
License: UNKNOWN
Platform: UNKNOWN
